[{"time":0.0,"pose":{"rotation":{"radians":0.0},"translation":{"x":1.0,"y":3.0}},"velocity":0,"acceleration":3.0,"curvature":0,"holonomicRotation":0.0,"angularVelocity":0.0,"holonomicAngularVelocity":0.0799274629659606},{"time":0.08890588281997949,"pose":{"rotation":{"radians":0.0},"translation":{"x":1.0118563839999999,"y":3.0}},"velocity":0.26671764845993845,"acceleration":2.9999999999999996,"curvature":0,"holonomicRotation":0.0071060216565499434,"angularVelocity":0.0,"holonomicAngularVelocity":0.5910486867025218},{"time":0.12497218890617237,"pose":{"rotation":{"radians":0.0},"translation":{"x":1.023427072,"y":3.0}},"velocity":0.3749165667185171,"acceleration":3.0,"curvature":0,"holonomicRotation":0.02842296450300541,"angularVelocity":0.0,"holonomicAngularVelocity":1.3081755564468873},{"time":0.15212794615060035,"pose":{"rotation":{"radians":0.0},"translation":{"x":1.034714368,"y":3.0}},"velocity":0.456383838451801,"acceleration":3.0,"curvature":0,"holonomicRotation":0.06394746234697157,"angularVelocity":0.0,"holonomicAngularVelocity":2.2141602030201954},{"time":0.17458632248833222,"pose":{"rotation":{"radians":0.0},"translation":{"x":1.045720576,"y":3.0}},"velocity":0.5237589674649966,"acceleration":2.9999999999999987,"curvature":0,"holonomicRotation":0.11367390545842793,"angularVelocity":0.0,"holonomicAngularVelocity":3.294301078603428},{"time":0.19398969044771436,"pose":{"rotation":{"radians":0.0},"translation":{"x":1.056448,"y":3.0}},"velocity":0.581969071343143,"acceleration":3.0,"curvature":0,"holonomicRotation":0.1775944414555597,"angularVelocity":0.0,"holonomicAngularVelocity":4.542080068115608},{"time":0.21118545404454364,"pose":{"rotation":{"radians":0.0},"translation":{"x":1.066898944,"y":3.0}},"velocity":0.6335563621336309,"acceleration":3.0,"curvature":0,"holonomicRotation":0.25569897654474594,"angularVelocity":0.0,"holonomicAngularVelocity":5.955411019836993},{"time":0.22667996823716008,"pose":{"rotation":{"radians":0.0},"translation":{"x":1.0770757119999999,"y":3.0}},"velocity":0.6800399047114802,"acceleration":3.0000000000000036,"curvature":0,"holonomicRotation":0.34797517711447457,"angularVelocity":0.0,"holonomicAngularVelocity":7.535057000459728},{"time":0.2408050497809382,"pose":{"rotation":{"radians":0.0},"translation":{"x":1.0869806080000002,"y":3.0}},"velocity":0.7224151493428146,"acceleration":3.0,"curvature":0,"holonomicRotation":0.45440847168298437,"angularVelocity":0.0,"holonomicAngularVelocity":9.283865972440488},{"time":0.25379248215815986,"pose":{"rotation":{"radians":0.0},"translation":{"x":1.0966159359999998,"y":3.0}},"velocity":0.7613774464744796,"acceleration":3.0,"curvature":0,"holonomicRotation":0.5749820531992444,"angularVelocity":0.0,"holonomicAngularVelocity":11.206375998797169},{"time":0.2658119636133782,"pose":{"rotation":{"radians":0.0},"translation":{"x":1.1059839999999999,"y":3.0}},"velocity":0.7974358908401346,"acceleration":2.9999999999999907,"curvature":0,"holonomicRotation":0.7096768816969912,"angularVelocity":0.0,"holonomicAngularVelocity":13.308612428210504},{"time":0.2769923031421633,"pose":{"rotation":{"radians":0.0},"translation":{"x":1.115087104,"y":3.0}},"velocity":0.8309769094264897,"acceleration":3.0,"curvature":0,"holonomicRotation":0.8584716873013931,"angularVelocity":0.0,"holonomicAngularVelocity":15.597997302545298},{"time":0.2874341107106114,"pose":{"rotation":{"radians":0.0},"translation":{"x":1.123927552,"y":3.0}},"velocity":0.8623023321318343,"acceleration":3.0000000000000107,"curvature":0,"holonomicRotation":1.0213429735877444,"angularVelocity":0.0,"holonomicAngularVelocity":18.083332042976405},{"time":0.2972178191158801,"pose":{"rotation":{"radians":0.0},"translation":{"x":1.132507648,"y":3.0}},"velocity":0.8916534573476402,"acceleration":3.0,"curvature":0,"holonomicRotation":1.1982650212918766,"angularVelocity":0.0,"holonomicAngularVelocity":20.774833606098213},{"time":0.3064089815915975,"pose":{"rotation":{"radians":0.0},"translation":{"x":1.140829696,"y":3.0}},"velocity":0.9192269447747926,"acceleration":3.000000000000006,"curvature":0,"holonomicRotation":1.3892098923715201,"angularVelocity":0.0,"holonomicAngularVelocity":23.684214230529154},{"time":0.31506189868024337,"pose":{"rotation":{"radians":0.0},"translation":{"x":1.148896,"y":3.0}},"velocity":0.9451856960407301,"acceleration":2.999999999999994,"curvature":0,"holonomicRotation":1.594147434418015,"angularVelocity":0.0,"holonomicAngularVelocity":26.824800596899564},{"time":0.3232221774569314,"pose":{"rotation":{"radians":0.0},"translation":{"x":1.156708864,"y":3.0}},"velocity":0.969666532370794,"acceleration":2.9999999999999862,"curvature":0,"holonomicRotation":1.8130452854177825,"angularVelocity":0.0,"holonomicAngularVelocity":30.21169189893299},{"time":0.3309285844408126,"pose":{"rotation":{"radians":0.0},"translation":{"x":1.164270592,"y":3.0}},"velocity":0.9927857533224377,"acceleration":3.000000000000007,"curvature":0,"holonomicRotation":2.0458688788625867,"angularVelocity":0.0,"holonomicAngularVelocity":33.861959037045814},{"time":0.3382144171971384,"pose":{"rotation":{"radians":0.0},"translation":{"x":1.171583488,"y":3.0}},"velocity":1.0146432515914152,"acceleration":3.0000000000000075,"curvature":0,"holonomicRotation":2.2925814492080585,"angularVelocity":0.0,"holonomicAngularVelocity":37.7948894705186},{"time":0.3451085394480989,"pose":{"rotation":{"radians":0.0},"translation":{"x":1.178649856,"y":3.0}},"velocity":1.0353256183442965,"acceleration":2.999999999999976,"curvature":0,"holonomicRotation":2.5531440376793526,"angularVelocity":0.0,"holonomicAngularVelocity":42.032284550935984},{"time":0.3516361756133746,"pose":{"rotation":{"radians":0.0},"translation":{"x":1.185472,"y":3.0}},"velocity":1.0549085268401237,"acceleration":3.0,"curvature":0,"holonomicRotation":2.827515498423203,"angularVelocity":0.0,"holonomicAngularVelocity":46.59881866441789},{"time":0.35781952993094157,"pose":{"rotation":{"radians":0.0},"translation":{"x":1.192052224,"y":3.0}},"velocity":1.0734585897928246,"acceleration":3.000000000000009,"curvature":0,"holonomicRotation":3.1156525050053507,"angularVelocity":0.0,"holonomicAngularVelocity":51.522472463370356},{"time":0.3636782754028622,"pose":{"rotation":{"radians":0.0},"translation":{"x":1.1983928320000001,"y":3.0}},"velocity":1.0910348262085865,"acceleration":3.0000000000000093,"curvature":0,"holonomicRotation":3.4175095572522762,"angularVelocity":0.0,"holonomicAngularVelocity":56.83505611690882},{"time":0.3692299446144639,"pose":{"rotation":{"radians":0.0},"translation":{"x":1.2044961280000002,"y":3.0}},"velocity":1.1076898338433918,"acceleration":3.00000000000003,"curvature":0,"holonomicRotation":3.7330389884361748,"angularVelocity":0.0,"holonomicAngularVelocity":62.57284315298251},{"time":0.3744902455338456,"pose":{"rotation":{"radians":0.0},"translation":{"x":1.210364416,"y":3.0}},"velocity":1.1234707366015368,"acceleration":3.0,"curvature":0,"holonomicRotation":4.062190972802134,"angularVelocity":0.0,"holonomicAngularVelocity":68.77734149751161},{"time":0.3794733192202056,"pose":{"rotation":{"radians":0.0},"translation":{"x":1.2160000000000002,"y":3.0}},"velocity":1.1384199576606169,"acceleration":2.999999999999989,"curvature":0,"holonomicRotation":4.404913533436182,"angularVelocity":0.0,"holonomicAngularVelocity":75.4962362724008},{"time":0.3841919520239851,"pose":{"rotation":{"radians":0.0},"translation":{"x":1.2214051840000002,"y":3.0}},"velocity":1.1525758560719555,"acceleration":3.0000000000000235,"curvature":0,"holonomicRotation":4.761152550473019,"angularVelocity":0.0,"holonomicAngularVelocity":82.78454954481703},{"time":0.38865775175596334,"pose":{"rotation":{"radians":0.0},"translation":{"x":1.2265822720000001,"y":3.0}},"velocity":1.16597325526789,"acceleration":2.999999999999975,"curvature":0,"holonomicRotation":5.130851769642203,"angularVelocity":0.0,"holonomicAngularVelocity":90.7060765942906},{"time":0.39288129504978986,"pose":{"rotation":{"radians":0.0},"translation":{"x":1.2315335680000001,"y":3.0}},"velocity":1.1786438851493697,"acceleration":3.0000000000000133,"curvature":0,"holonomicRotation":5.513952811151333,"angularVelocity":0.0,"holonomicAngularVelocity":99.33517792939205},{"time":0.3968722514865457,"pose":{"rotation":{"radians":0.0},"translation":{"x":1.236261376,"y":3.0}},"velocity":1.1906167544596373,"acceleration":3.000000000000028,"curvature":0,"holonomicRotation":5.910395178904928,"angularVelocity":0.0,"holonomicAngularVelocity":108.75903351742608},{"time":0.4006394888175652,"pose":{"rotation":{"radians":0.0},"translation":{"x":1.240768,"y":3.0}},"velocity":1.2019184664526958,"acceleration":2.9999999999999853,"curvature":0,"holonomicRotation":6.320116270057379,"angularVelocity":0.0,"holonomicAngularVelocity":119.08050388209962},{"time":0.40419116269408956,"pose":{"rotation":{"radians":0.0},"translation":{"x":1.245055744,"y":3.0}},"velocity":1.2125734880822687,"acceleration":2.999999999999969,"curvature":0,"holonomicRotation":6.743051384898786,"angularVelocity":0.0,"holonomicAngularVelocity":130.4217970162615},{"time":0.40753479360663186,"pose":{"rotation":{"radians":0.0},"translation":{"x":1.2491269120000001,"y":3.0}},"velocity":1.2226043808198956,"acceleration":3.0,"curvature":0,"holonomicRotation":7.179133737071676,"angularVelocity":0.0,"holonomicAngularVelocity":142.92921837344778},{"time":0.41067733319480887,"pose":{"rotation":{"radians":0.0},"translation":{"x":1.2529838080000002,"y":3.0}},"velocity":1.2320319995844267,"acceleration":3.0,"curvature":0,"holonomicRotation":7.628294464117432,"angularVelocity":0.0,"holonomicAngularVelocity":156.77939597019898},{"time":0.4136252216681183,"pose":{"rotation":{"radians":0.0},"translation":{"x":1.2566287360000001,"y":3.0}},"velocity":1.240875665004355,"acceleration":3.0000000000000187,"curvature":0,"holonomicRotation":8.0904626383504,"angularVelocity":0.0,"holonomicAngularVelocity":172.18754374002532},{"time":0.4163844377495393,"pose":{"rotation":{"radians":0.0},"translation":{"x":1.260064,"y":3.0}},"velocity":1.2491533132486181,"acceleration":3.00000000000002,"curvature":0,"holonomicRotation":8.565565278058259,"angularVelocity":0.0,"holonomicAngularVelocity":189.4185862353394},{"time":0.41896054229485624,"pose":{"rotation":{"radians":0.0},"translation":{"x":1.2632919040000001,"y":3.0}},"velocity":1.2568816268845688,"acceleration":2.9999999999999782,"curvature":0,"holonomicRotation":9.053527359026623,"angularVelocity":0.0,"holonomicAngularVelocity":208.80237098002294},{"time":0.42135871653497325,"pose":{"rotation":{"radians":0.0},"translation":{"x":1.266314752,"y":3.0}},"velocity":1.2640761496049198,"acceleration":2.999999999999954,"curvature":0,"holonomicRotation":9.55427182638627,"angularVelocity":0.0,"holonomicAngularVelocity":230.7548346654791},{"time":0.4235837957240575,"pose":{"rotation":{"radians":0.0},"translation":{"x":1.2691348480000002,"y":3.0}},"velocity":1.2707513871721725,"acceleration":2.999999999999975,"curvature":0,"holonomicRotation":10.067719606781008,"angularVelocity":0.0,"holonomicAngularVelocity":255.8080311061383},{"time":0.42564029884398863,"pose":{"rotation":{"radians":0.0},"translation":{"x":1.271754496,"y":3.0}},"velocity":1.2769208965319658,"acceleration":3.0,"curvature":0,"holonomicRotation":10.593789620854215,"angularVelocity":0.0,"holonomicAngularVelocity":284.6536738324903},{"time":0.4275324549083963,"pose":{"rotation":{"radians":0.0},"translation":{"x":1.274176,"y":3.0}},"velocity":1.282597364725189,"acceleration":3.0000000000000293,"curvature":0,"holonomicRotation":11.132398796052287,"angularVelocity":0.0,"holonomicAngularVelocity":318.20786467359716},{"time":0.4292642263222037,"pose":{"rotation":{"radians":0.0},"translation":{"x":1.2764016640000002,"y":3.0}},"velocity":1.287792678966611,"acceleration":2.999999999999968,"curvature":0,"holonomicRotation":11.683462079742707,"angularVelocity":0.0,"holonomicAngularVelocity":357.71009549597255},{"time":0.43083932968103095,"pose":{"rotation":{"radians":0.0},"translation":{"x":1.2784337920000002,"y":3.0}},"velocity":1.292517989043093,"acceleration":3.0000000000000706,"curvature":0,"holonomicRotation":12.246892452644836,"angularVelocity":0.0,"holonomicAngularVelocity":404.87974378704604},{"time":0.43226125433584717,"pose":{"rotation":{"radians":0.0},"translation":{"x":1.280274688,"y":3.0}},"velocity":1.2967837630075416,"acceleration":3.000000000000039,"curvature":0,"holonomicRotation":12.822600942571311,"angularVelocity":0.0,"holonomicAngularVelocity":462.17318951135303},{"time":0.4335332789994327,"pose":{"rotation":{"radians":0.0},"translation":{"x":1.281926656,"y":3.0}},"velocity":1.300599836998298,"acceleration":2.9999999999998255,"curvature":0,"holonomicRotation":13.410496638477754,"angularVelocity":0.0,"holonomicAngularVelocity":533.2260906554686},{"time":0.43465848663059603,"pose":{"rotation":{"radians":0.0},"translation":{"x":1.283392,"y":3.0}},"velocity":1.303975459891788,"acceleration":3.0000000000000986,"curvature":0,"holonomicRotation":14.010486704818664,"angularVelocity":0.0,"holonomicAngularVelocity":623.6575968878151},{"time":0.4356397777981254,"pose":{"rotation":{"radians":0.0},"translation":{"x":1.2846730240000002,"y":3.0}},"velocity":1.3069193333943763,"acceleration":3.0000000000000564,"curvature":0,"holonomicRotation":14.622476396207272,"angularVelocity":0.0,"holonomicAngularVelocity":742.6366353935028},{"time":0.43647988269793153,"pose":{"rotation":{"radians":0.0},"translation":{"x":1.2857720320000001,"y":3.0}},"velocity":1.3094396480937947,"acceleration":3.0,"curvature":0,"holonomicRotation":15.24636907237689,"angularVelocity":0.0,"holonomicAngularVelocity":906.2107773554123},{"time":0.4371813719727775,"pose":{"rotation":{"radians":0.0},"translation":{"x":1.286691328,"y":3.0}},"velocity":1.3115441159183325,"acceleration":2.999999999999921,"curvature":0,"holonomicRotation":15.882066213441549,"angularVelocity":0.0,"holonomicAngularVelocity":1145.245942628112},{"time":0.4377466664636065,"pose":{"rotation":{"radians":0.0},"translation":{"x":1.287433216,"y":3.0}},"velocity":1.3132399993908195,"acceleration":3.0,"curvature":0,"holonomicRotation":16.529467435453466,"angularVelocity":0.0,"holonomicAngularVelocity":1527.6641771121185},{"time":0.4381780460041329,"pose":{"rotation":{"radians":0.0},"translation":{"x":1.288,"y":3.0}},"velocity":1.3145341380123987,"acceleration":3.0,"curvature":0,"holonomicRotation":17.18847050625475,"angularVelocity":0.0,"holonomicAngularVelocity":2237.9020428411295},{"time":0.43847765735553734,"pose":{"rotation":{"radians":0.0},"translation":{"x":1.288393984,"y":3.0}},"velocity":1.315432972066612,"acceleration":3.0,"curvature":0,"holonomicRotation":17.858971361621133,"angularVelocity":0.0,"holonomicAngularVelocity":4014.3451262345925},{"time":0.43864752136538976,"pose":{"rotation":{"radians":0.0},"translation":{"x":1.288617472,"y":3.0}},"velocity":1.3159425640961693,"acceleration":3.0,"curvature":0,"holonomicRotation":18.540864121694845,"angularVelocity":0.0,"holonomicAngularVelocity":16497.120755002292},{"time":0.43868953942395306,"pose":{"rotation":{"radians":0.0},"translation":{"x":1.288672768,"y":3.0}},"velocity":1.316068618271859,"acceleration":2.9999999999973577,"curvature":0,"holonomicRotation":19.23404110770433,"angularVelocity":37389.209497636206,"holonomicAngularVelocity":8382.74025053154},{"time":0.4387735634698155,"pose":{"rotation":{"radians":3.141592653589793},"translation":{"x":1.288562176,"y":3.0}},"velocity":1.3163206904094462,"acceleration":2.999999999998018,"curvature":0,"holonomicRotation":19.93839285896792,"angularVelocity":0.0,"holonomicAngularVelocity":3435.5283374525256},{"time":0.4389818037231157,"pose":{"rotation":{"radians":3.141592653589793},"translation":{"x":1.288288,"y":3.0}},"velocity":1.3169454111693468,"acceleration":3.0000000000002665,"curvature":0,"holonomicRotation":20.653808150178996,"angularVelocity":0.0,"holonomicAngularVelocity":2197.568330462168},{"time":0.4393123353606179,"pose":{"rotation":{"radians":3.141592653589793},"translation":{"x":1.2878525440000002,"y":3.0}},"velocity":1.3179370060818536,"acceleration":3.000000000000168,"curvature":0,"holonomicRotation":21.38017400896972,"angularVelocity":0.0,"holonomicAngularVelocity":1635.3156135942297},{"time":0.4397631362449565,"pose":{"rotation":{"radians":3.141592653589793},"translation":{"x":1.287258112,"y":3.0}},"velocity":1.3192894087348692,"acceleration":2.9999999999997535,"curvature":0,"holonomicRotation":22.11737573375068,"angularVelocity":0.0,"holonomicAngularVelocity":1314.5487054387875},{"time":0.44033209285719804,"pose":{"rotation":{"radians":3.141592653589793},"translation":{"x":1.286507008,"y":3.0}},"velocity":1.3209962785715939,"acceleration":3.0,"curvature":0,"holonomicRotation":22.86529691182364,"angularVelocity":0.0,"holonomicAngularVelocity":1107.4718131441061},{"time":0.44101700647480724,"pose":{"rotation":{"radians":3.141592653589793},"translation":{"x":1.285601536,"y":3.0}},"velocity":1.3230510194244214,"acceleration":2.9999999999999187,"curvature":0,"holonomicRotation":23.623819437764386,"angularVelocity":0.0,"holonomicAngularVelocity":962.9486210642767},{"time":0.4418155995435202,"pose":{"rotation":{"radians":3.141592653589793},"translation":{"x":1.284544,"y":3.0}},"velocity":1.3254467986305603,"acceleration":3.0000000000000697,"curvature":0,"holonomicRotation":24.392823532073,"angularVelocity":0.0,"holonomicAngularVelocity":856.517012177392},{"time":0.44272552219179795,"pose":{"rotation":{"radians":3.141592653589793},"translation":{"x":1.2833367039999999,"y":3.0}},"velocity":1.3281765665753935,"acceleration":2.999999999999939,"curvature":0,"holonomicRotation":25.172187760088416,"angularVelocity":0.0,"holonomicAngularVelocity":775.0028373022699},{"time":0.443744358837383,"pose":{"rotation":{"radians":3.141592653589793},"translation":{"x":1.281981952,"y":3.0}},"velocity":1.3312330765121487,"acceleration":3.0000000000000546,"curvature":0,"holonomicRotation":25.96178905116436,"angularVelocity":0.0,"holonomicAngularVelocity":710.6822390381266},{"time":0.44486963483699377,"pose":{"rotation":{"radians":3.141592653589793},"translation":{"x":1.2804820479999999,"y":3.0}},"velocity":1.334608904510981,"acceleration":3.0,"curvature":0,"holonomicRotation":26.761502718103603,"angularVelocity":0.0,"holonomicAngularVelocity":658.7271957053273},{"time":0.44609882313227434,"pose":{"rotation":{"radians":3.141592653589793},"translation":{"x":1.278839296,"y":3.0}},"velocity":1.3382964693968227,"acceleration":2.9999999999999547,"curvature":0,"holonomicRotation":27.571202476847585,"angularVelocity":0.0,"holonomicAngularVelocity":615.9646131867245},{"time":0.44742935084770663,"pose":{"rotation":{"radians":3.141592653589793},"translation":{"x":1.277056,"y":3.0}},"velocity":1.3422880525431196,"acceleration":3.0,"curvature":0,"holonomicRotation":28.390760466418055,"angularVelocity":0.0,"holonomicAngularVelocity":580.2231448099768},{"time":0.4488586057991984,"pose":{"rotation":{"radians":3.141592653589793},"translation":{"x":1.275134464,"y":3.0}},"velocity":1.3465758173975948,"acceleration":2.9999999999999614,"curvature":0,"holonomicRotation":29.220047269107837,"angularVelocity":0.0,"holonomicAngularVelocity":549.9667417075547},{"time":0.4503839428754095,"pose":{"rotation":{"radians":3.141592653589793},"translation":{"x":1.273076992,"y":3.0}},"velocity":1.351151828626228,"acceleration":2.9999999999999636,"curvature":0,"holonomicRotation":30.05893193091739,"angularVelocity":0.0,"holonomicAngularVelocity":524.0780993455351},{"time":0.45200269025748097,"pose":{"rotation":{"radians":3.141592653589793},"translation":{"x":1.2708858879999998,"y":3.0}},"velocity":1.3560080707724425,"acceleration":3.0,"curvature":0,"holonomicRotation":30.90728198223396,"angularVelocity":0.0,"holonomicAngularVelocity":501.7250318842818},{"time":0.45371215544660054,"pose":{"rotation":{"radians":3.141592653589793},"translation":{"x":1.2685634559999999,"y":3.0}},"velocity":1.3611364663398013,"acceleration":3.0000000000000973,"curvature":0,"holonomicRotation":31.76496345875005,"angularVelocity":0.0,"holonomicAngularVelocity":482.2749478624081},{"time":0.4555096310727142,"pose":{"rotation":{"radians":3.141592653589793},"translation":{"x":1.266112,"y":3.0}},"velocity":1.3665288932181423,"acceleration":3.0,"curvature":0,"holonomicRotation":32.63184092261796,"angularVelocity":0.0,"holonomicAngularVelocity":465.23836981958647},{"time":0.4573924004615733,"pose":{"rotation":{"radians":3.141592653589793},"translation":{"x":1.2635338239999998,"y":3.0}},"velocity":1.3721772013847195,"acceleration":2.999999999999941,"curvature":0,"holonomicRotation":33.507777483836996,"angularVelocity":0.0,"holonomicAngularVelocity":450.2306072463202},{"time":0.45935774294116366,"pose":{"rotation":{"radians":3.141592653589793},"translation":{"x":1.260831232,"y":3.0}},"velocity":1.3780732288234905,"acceleration":2.9999999999999436,"curvature":0,"holonomicRotation":34.39263482186995,"angularVelocity":0.0,"holonomicAngularVelocity":436.9451219848722},{"time":0.4614029388723052,"pose":{"rotation":{"radians":3.141592653589793},"translation":{"x":1.258006528,"y":3.0}},"velocity":1.384208816616915,"acceleration":2.999999999999973,"curvature":0,"holonomicRotation":35.28627320748556,"angularVelocity":0.0,"holonomicAngularVelocity":425.134626003654},{"time":0.4635252743918073,"pose":{"rotation":{"radians":3.141592653589793},"translation":{"x":1.255062016,"y":3.0}},"velocity":1.3905758231754213,"acceleration":2.999999999999974,"curvature":0,"holonomicRotation":36.188551524823346,"angularVelocity":0.0,"holonomicAngularVelocity":414.597413546137},{"time":0.4657220458599746,"pose":{"rotation":{"radians":3.141592653589793},"translation":{"x":1.2519999999999998,"y":3.0}},"velocity":1.3971661375799234,"acceleration":3.0000000000000506,"curvature":0,"holonomicRotation":37.09932729367747,"angularVelocity":0.0,"holonomicAngularVelocity":405.16731124503127},{"time":0.4679905640074385,"pose":{"rotation":{"radians":3.141592653589793},"translation":{"x":1.2488227839999997,"y":3.0}},"velocity":1.4039716920223149,"acceleration":2.999999999999951,"curvature":0,"holonomicRotation":38.018456691995965,"angularVelocity":0.0,"holonomicAngularVelocity":396.706176149246},{"time":0.4703281577792257,"pose":{"rotation":{"radians":3.141592653589793},"translation":{"x":1.245532672,"y":3.0}},"velocity":1.4109844733376764,"acceleration":2.9999999999999525,"curvature":0,"holonomicRotation":38.945794578591965,"angularVelocity":0.0,"holonomicAngularVelocity":389.0982186353148},{"time":0.4727321778766497,"pose":{"rotation":{"radians":3.141592653589793},"translation":{"x":1.2421319679999998,"y":3.0}},"velocity":1.4181965336299482,"acceleration":2.999999999999977,"curvature":0,"holonomicRotation":39.881194516063125,"angularVelocity":0.0,"holonomicAngularVelocity":382.2456525237462},{"time":0.47520000000000034,"pose":{"rotation":{"radians":3.141592653589793},"translation":{"x":1.2386229759999998,"y":3.0}},"velocity":1.4256000000000002,"acceleration":2.9999999999999774,"curvature":0,"holonomicRotation":40.82450879391584,"angularVelocity":0.0,"holonomicAngularVelocity":376.06532401511964},{"time":0.4777290277971399,"pose":{"rotation":{"radians":3.141592653589793},"translation":{"x":1.2350079999999997,"y":3.0}},"velocity":1.4331870833914189,"acceleration":3.0000000000000218,"curvature":0,"holonomicRotation":41.775588451890364,"angularVelocity":0.0,"holonomicAngularVelocity":370.486071798381},{"time":0.4803166955249426,"pose":{"rotation":{"radians":3.141592653589793},"translation":{"x":1.2312893439999997,"y":3.0}},"velocity":1.440950086574827,"acceleration":3.0,"curvature":0,"holonomicRotation":42.73428330348344,"angularVelocity":0.0,"holonomicAngularVelocity":365.44663978899445},{"time":0.4829604704321052,"pose":{"rotation":{"radians":3.141592653589793},"translation":{"x":1.2274693119999998,"y":3.0}},"velocity":1.4488814112963149,"acceleration":3.0,"curvature":0,"holonomicRotation":43.700441959664474,"angularVelocity":0.0,"holonomicAngularVelocity":360.8940121030988},{"time":0.48565785487316104,"pose":{"rotation":{"radians":3.141592653589793},"translation":{"x":1.2235502079999998,"y":3.0}},"velocity":1.4569735646194824,"acceleration":3.0,"curvature":0,"holonomicRotation":44.673911852781586,"angularVelocity":0.0,"holonomicAngularVelocity":356.782073887491},{"time":0.48840638816461074,"pose":{"rotation":{"radians":3.141592653589793},"translation":{"x":1.2195343359999997,"y":3.0}},"velocity":1.4652191644938313,"acceleration":2.9999999999999396,"curvature":0,"holonomicRotation":45.65453926065382,"angularVelocity":0.0,"holonomicAngularVelocity":353.07052597539354},{"time":0.4912036481949218,"pose":{"rotation":{"radians":3.141592653589793},"translation":{"x":1.2154239999999996,"y":3.0}},"velocity":1.4736109445847643,"acceleration":2.9999999999999405,"curvature":0,"holonomicRotation":46.64216933084569,"angularVelocity":0.0,"holonomicAngularVelocity":349.7239989781757},{"time":0.4940472528007827,"pose":{"rotation":{"radians":3.141592653589793},"translation":{"x":1.2112215039999996,"y":3.0}},"velocity":1.4821417584023469,"acceleration":2.9999999999999414,"curvature":0,"holonomicRotation":47.63664610512013,"angularVelocity":0.0,"holonomicAngularVelocity":346.7113253487223},{"time":0.49693486092243566,"pose":{"rotation":{"radians":3.141592653589793},"translation":{"x":1.2069291519999996,"y":3.0}},"velocity":1.4908045827673058,"acceleration":3.000000000000019,"curvature":0,"holonomicRotation":48.63781254406616,"angularVelocity":0.0,"holonomicAngularVelocity":344.00493752155865},{"time":0.4998641735511762,"pose":{"rotation":{"radians":3.141592653589793},"translation":{"x":1.2025492479999997,"y":3.0}},"velocity":1.4995925206535274,"acceleration":3.0000000000000377,"curvature":0,"holonomicRotation":49.645510551897154,"angularVelocity":0.0,"holonomicAngularVelocity":341.5803673899868},{"time":0.5028329344822199,"pose":{"rotation":{"radians":3.141592653589793},"translation":{"x":1.1980840959999997,"y":3.0}},"velocity":1.5084988034466587,"acceleration":3.0000000000000373,"curvature":0,"holonomicRotation":50.6595810014161,"angularVelocity":0.0,"holonomicAngularVelocity":339.41582777939243},{"time":0.5058389308861077,"pose":{"rotation":{"radians":3.141592653589793},"translation":{"x":1.1935359999999997,"y":3.0}},"velocity":1.517516792658322,"acceleration":3.0,"curvature":0,"holonomicRotation":51.679863759143544,"angularVelocity":0.0,"holonomicAngularVelocity":337.4918606844107},{"time":0.508879993711681,"pose":{"rotation":{"radians":3.141592653589793},"translation":{"x":1.1889072639999996,"y":3.0}},"velocity":1.526639981135042,"acceleration":2.9999999999999636,"curvature":0,"holonomicRotation":52.70619771060449,"angularVelocity":0.0,"holonomicAngularVelocity":335.79104019118364},{"time":0.5119539979334085,"pose":{"rotation":{"radians":3.141592653589793},"translation":{"x":1.1842001919999998,"y":3.0}},"velocity":1.5358619938002243,"acceleration":3.0,"curvature":0,"holonomicRotation":53.73842078577044,"angularVelocity":0.0,"holonomicAngularVelocity":334.2977204413159},{"time":0.5150588626555226,"pose":{"rotation":{"radians":3.141592653589793},"translation":{"x":1.1794170879999997,"y":3.0}},"velocity":1.5451765879665667,"acceleration":3.0,"curvature":0,"holonomicRotation":54.77636998465185,"angularVelocity":0.0,"holonomicAngularVelocity":332.9978208949393},{"time":0.5181925510850194,"pose":{"rotation":{"radians":3.141592653589793},"translation":{"x":1.1745602559999997,"y":3.0}},"velocity":1.554577653255057,"acceleration":3.0,"curvature":0,"holonomicRotation":55.81988140303797,"angularVelocity":0.0,"holonomicAngularVelocity":331.8786426347581},{"time":0.5213530703851282,"pose":{"rotation":{"radians":3.141592653589793},"translation":{"x":1.1696319999999996,"y":3.0}},"velocity":1.5640592111553837,"acceleration":3.000000000000035,"curvature":0,"holonomicRotation":56.86879025837905,"angularVelocity":0.0,"holonomicAngularVelocity":330.9287106306535},{"time":0.5245384714203529,"pose":{"rotation":{"radians":3.141592653589793},"translation":{"x":1.1646346239999996,"y":3.0}},"velocity":1.5736154142610579,"acceleration":3.0000000000000346,"curvature":0,"holonomicRotation":57.922930915807505,"angularVelocity":0.0,"holonomicAngularVelocity":330.1376378136244},{"time":0.5277468484036644,"pose":{"rotation":{"radians":3.141592653589793},"translation":{"x":1.1595704319999998,"y":3.0}},"velocity":1.5832405452109923,"acceleration":3.0000000000000346,"curvature":0,"holonomicRotation":58.98213691429355,"angularVelocity":0.0,"holonomicAngularVelocity":329.4960075544069},{"time":0.5309763384558679,"pose":{"rotation":{"radians":3.141592653589793},"translation":{"x":1.1544417279999997,"y":3.0}},"velocity":1.5929290153676028,"acceleration":2.999999999999966,"curvature":0,"holonomicRotation":60.04624099293128,"angularVelocity":0.0,"holonomicAngularVelocity":328.9952717386295},{"time":0.5342251210866076,"pose":{"rotation":{"radians":3.141592653589793},"translation":{"x":1.1492508159999995,"y":3.0}},"velocity":1.6026753632598219,"acceleration":3.0,"curvature":0,"holonomicRotation":61.115075117351225,"angularVelocity":0.0,"holonomicAngularVelocity":328.62766211316324},{"time":0.5374914176059005,"pose":{"rotation":{"radians":3.141592653589793},"translation":{"x":1.1439999999999995,"y":3.0}},"velocity":1.6124742528177007,"acceleration":3.000000000000068,"curvature":0,"holonomicRotation":62.18847050625481,"angularVelocity":0.0,"holonomicAngularVelocity":328.38611297014063},{"time":0.5407734904745243,"pose":{"rotation":{"radians":3.141592653589793},"translation":{"x":1.1386915839999996,"y":3.0}},"velocity":1.6223204714235722,"acceleration":3.0,"curvature":0,"holonomicRotation":63.26625765806694,"angularVelocity":0.0,"holonomicAngularVelocity":328.264193554069},{"time":0.5440696426010189,"pose":{"rotation":{"radians":3.141592653589793},"translation":{"x":1.1333278719999995,"y":3.0}},"velocity":1.632208927803056,"acceleration":3.0000000000000338,"curvature":0,"holonomicRotation":64.34826637770222,"angularVelocity":0.0,"holonomicAngularVelocity":328.2560488387456},{"time":0.5473782165925133,"pose":{"rotation":{"radians":3.141592653589793},"translation":{"x":1.1279111679999996,"y":3.0}},"velocity":1.642134649777539,"acceleration":2.999999999999933,"curvature":0,"holonomicRotation":65.43432580344081,"angularVelocity":0.0,"holonomicAngularVelocity":328.35634753575687},{"time":0.5506975939660537,"pose":{"rotation":{"radians":3.141592653589793},"translation":{"x":1.1224437759999994,"y":3.0}},"velocity":1.6520927818981601,"acceleration":2.9999999999999667,"curvature":0,"holonomicRotation":66.52426443390937,"angularVelocity":0.0,"holonomicAngularVelocity":328.56023637477443},{"time":0.5540261943265864,"pose":{"rotation":{"radians":3.141592653589793},"translation":{"x":1.1169279999999995,"y":3.0}},"velocity":1.6620785829797584,"acceleration":3.0000000000000333,"curvature":0,"holonomicRotation":67.61791015516316,"angularVelocity":0.0,"holonomicAngularVelocity":328.8632998420432},{"time":0.5573624745172574,"pose":{"rotation":{"radians":3.141592653589793},"translation":{"x":1.1113661439999996,"y":3.0}},"velocity":1.6720874235517715,"acceleration":3.0000000000000333,"curvature":0,"holonomicRotation":68.71509026786487,"angularVelocity":0.0,"holonomicAngularVelocity":329.2615246878308},{"time":0.5607049277472068,"pose":{"rotation":{"radians":3.141592653589793},"translation":{"x":1.1057605119999996,"y":3.0}},"velocity":1.6821147832416197,"acceleration":2.9999999999999667,"curvature":0,"holonomicRotation":69.81563151455578,"angularVelocity":0.0,"holonomicAngularVelocity":329.75126861524416},{"time":0.5640520827015892,"pose":{"rotation":{"radians":3.141592653589793},"translation":{"x":1.1001134079999995,"y":3.0}},"velocity":1.6921562481047672,"acceleration":3.000000000000066,"curvature":0,"holonomicRotation":70.91936010701518,"angularVelocity":0.0,"holonomicAngularVelocity":330.32923264975244},{"time":0.5674025026381189,"pose":{"rotation":{"radians":3.141592653589793},"translation":{"x":1.0944271359999995,"y":3.0}},"velocity":1.702207507914356,"acceleration":2.9999999999999667,"curvature":0,"holonomicRotation":72.02610175370344,"angularVelocity":0.0,"holonomicAngularVelocity":330.99243676170727},{"time":0.5707547844740336,"pose":{"rotation":{"radians":3.141592653589793},"translation":{"x":1.0887039999999994,"y":3.0}},"velocity":1.7122643534221,"acceleration":2.9999999999999667,"curvature":0,"holonomicRotation":73.13568168728487,"angularVelocity":0.0,"holonomicAngularVelocity":331.73819837530806},{"time":0.5741075578669911,"pose":{"rotation":{"radians":3.141592653589793},"translation":{"x":1.0829463039999996,"y":3.0}},"velocity":1.7223226736009725,"acceleration":3.0,"curvature":0,"holonomicRotation":74.24792469222525,"angularVelocity":0.0,"holonomicAngularVelocity":332.56411345054914},{"time":0.5774594842930547,"pose":{"rotation":{"radians":3.141592653589793},"translation":{"x":1.0771563519999994,"y":3.0}},"velocity":1.7323784528791633,"acceleration":2.9999999999999667,"curvature":0,"holonomicRotation":75.36265513246057,"angularVelocity":0.0,"holonomicAngularVelocity":333.46803986917575},{"time":0.580809256124591,"pose":{"rotation":{"radians":3.141592653589793},"translation":{"x":1.0713364479999994,"y":3.0}},"velocity":1.7424277683737721,"acceleration":3.0,"curvature":0,"holonomicRotation":76.47969697913196,"angularVelocity":0.0,"holonomicAngularVelocity":334.4480828937592},{"time":0.5841555957105955,"pose":{"rotation":{"radians":3.141592653589793},"translation":{"x":1.0654888959999995,"y":3.0}},"velocity":1.7524667871317856,"acceleration":3.0,"curvature":0,"holonomicRotation":77.59887383838266,"angularVelocity":0.0,"holonomicAngularVelocity":335.50258250319985},{"time":0.5874972544616704,"pose":{"rotation":{"radians":3.141592653589793},"translation":{"x":1.0596159999999994,"y":3.0}},"velocity":1.7624917633850103,"acceleration":2.9999999999999667,"curvature":0,"holonomicRotation":78.72000897921272,"angularVelocity":0.0,"holonomicAngularVelocity":336.63010243557915},{"time":0.5908330119416151,"pose":{"rotation":{"radians":3.141592653589793},"translation":{"x":1.0537200639999995,"y":3.0}},"velocity":1.7724990358248445,"acceleration":3.0000000000000666,"curvature":0,"holonomicRotation":79.84292536138673,"angularVelocity":0.0,"holonomicAngularVelocity":337.82942079500356},{"time":0.5941616749673448,"pose":{"rotation":{"radians":3.141592653589793},"translation":{"x":1.0478033919999994,"y":3.0}},"velocity":1.7824850249020339,"acceleration":3.0000000000000333,"curvature":0,"holonomicRotation":80.96744566339076,"angularVelocity":0.0,"holonomicAngularVelocity":339.0995221010238},{"time":0.5974820767186249,"pose":{"rotation":{"radians":3.141592653589793},"translation":{"x":1.0418682879999994,"y":3.0}},"velocity":1.792446230155874,"acceleration":3.0,"curvature":0,"holonomicRotation":82.09339231043322,"angularVelocity":0.0,"holonomicAngularVelocity":340.439590678495},{"time":0.6007930758589024,"pose":{"rotation":{"radians":3.141592653589793},"translation":{"x":1.0359170559999993,"y":3.0}},"velocity":1.8023792275767063,"acceleration":2.999999999999933,"curvature":0,"holonomicRotation":83.22058750248615,"angularVelocity":0.0,"holonomicAngularVelocity":341.84900530352684},{"time":0.6040935556683258,"pose":{"rotation":{"radians":3.141592653589793},"translation":{"x":1.0299519999999995,"y":3.0}},"velocity":1.8122806670049767,"acceleration":3.000000000000067,"curvature":0,"holonomicRotation":84.34885324236191,"angularVelocity":0.0,"holonomicAngularVelocity":343.3273350360028},{"time":0.607382423189872,"pose":{"rotation":{"radians":3.141592653589793},"translation":{"x":1.0239754239999994,"y":3.0}},"velocity":1.8221472695696153,"acceleration":2.9999999999999662,"curvature":0,"holonomicRotation":85.47801136382084,"angularVelocity":0.0,"holonomicAngularVelocity":344.87433618524284},{"time":0.6106586083893363,"pose":{"rotation":{"radians":3.141592653589793},"translation":{"x":1.0179896319999995,"y":3.0}},"velocity":1.831975825168008,"acceleration":3.0,"curvature":0,"holonomicRotation":86.607883559706,"angularVelocity":0.0,"holonomicAngularVelocity":346.48995036561627},{"time":0.6139210633298069,"pose":{"rotation":{"radians":3.141592653589793},"translation":{"x":1.0119969279999994,"y":3.0}},"velocity":1.84176318998942,"acceleration":3.000000000000034,"curvature":0,"holonomicRotation":87.73829141009972,"angularVelocity":0.0,"holonomicAngularVelocity":348.1743036148631},{"time":0.6171687613611052,"pose":{"rotation":{"radians":3.141592653589793},"translation":{"x":1.0059996159999993,"y":3.0}},"velocity":1.851506284083315,"acceleration":3.0,"curvature":0,"holonomicRotation":88.86905641049837,"angularVelocity":0.0,"holonomicAngularVelocity":348.11713992062977},{"time":0.6204175057054934,"pose":{"rotation":{"radians":3.141592653589793},"translation":{"x":0.9999999999999996,"y":3.0}},"velocity":1.841992104217608,"acceleration":-2.9285714285710744,"curvature":0,"holonomicRotation":90.0000000000001,"angularVelocity":0.0,"holonomicAngularVelocity":346.2969921991466},{"time":0.6236833255508224,"pose":{"rotation":{"radians":3.141592653589793},"translation":{"x":0.9940003839999996,"y":3.0}},"velocity":1.832194644681621,"acceleration":-2.999999999999932,"curvature":0,"holonomicRotation":91.13094358950183,"angularVelocity":0.0,"holonomicAngularVelocity":344.52345148335456},{"time":0.6269654388453749,"pose":{"rotation":{"radians":3.141592653589793},"translation":{"x":0.9880030719999996,"y":3.0}},"velocity":1.8223483047979638,"acceleration":-2.9999999999998983,"curvature":0,"holonomicRotation":92.26170858990046,"angularVelocity":0.0,"holonomicAngularVelocity":342.81781943234614},{"time":0.6302628399322423,"pose":{"rotation":{"radians":3.141592653589793},"translation":{"x":0.9820103679999994,"y":3.0}},"velocity":1.812456101537362,"acceleration":-2.9999999999999325,"curvature":0,"holonomicRotation":93.39211644029419,"angularVelocity":0.0,"holonomicAngularVelocity":341.1797674468599},{"time":0.6335745022982152,"pose":{"rotation":{"radians":3.141592653589793},"translation":{"x":0.9760245759999995,"y":3.0}},"velocity":1.8025211144394433,"acceleration":-2.9999999999999667,"curvature":0,"holonomicRotation":94.52198863617934,"angularVelocity":0.0,"holonomicAngularVelocity":339.6091491684837},{"time":0.636899377744662,"pose":{"rotation":{"radians":3.141592653589793},"translation":{"x":0.9700479999999995,"y":3.0}},"velocity":1.7925464881001028,"acceleration":-3.0000000000000666,"curvature":0,"holonomicRotation":95.65114675763832,"angularVelocity":0.0,"holonomicAngularVelocity":338.10600024180394},{"time":0.6402363955410596,"pose":{"rotation":{"radians":3.141592653589793},"translation":{"x":0.9640829439999995,"y":3.0}},"velocity":1.7825354347109097,"acceleration":-3.0000000000000666,"curvature":0,"holonomicRotation":96.77941249751403,"angularVelocity":0.0,"holonomicAngularVelocity":336.6705391066679},{"time":0.6435844615614601,"pose":{"rotation":{"radians":3.141592653589793},"translation":{"x":0.9581317119999995,"y":3.0}},"velocity":1.772491236649708,"acceleration":-3.0000000000000333,"curvature":0,"holonomicRotation":97.90660768956698,"angularVelocity":0.0,"holonomicAngularVelocity":335.3031688371213},{"time":0.6469424574042891,"pose":{"rotation":{"radians":3.141592653589793},"translation":{"x":0.9521966079999995,"y":3.0}},"velocity":1.7624172491212209,"acceleration":-3.000000000000033,"curvature":0,"holonomicRotation":99.03255433660944,"angularVelocity":0.0,"holonomicAngularVelocity":334.0044800551791},{"time":0.650309239496009,"pose":{"rotation":{"radians":3.141592653589793},"translation":{"x":0.9462799359999995,"y":3.0}},"velocity":1.752316902846061,"acceleration":-3.000000000000033,"curvature":0,"holonomicRotation":100.15707463861344,"angularVelocity":0.0,"holonomicAngularVelocity":332.77525495936226},{"time":0.6536836381793221,"pose":{"rotation":{"radians":3.141592653589793},"translation":{"x":0.9403839999999994,"y":3.0}},"velocity":1.742193706796122,"acceleration":-3.0,"curvature":0,"holonomicRotation":101.27999102078746,"angularVelocity":0.0,"holonomicAngularVelocity":331.61647252118297},{"time":0.6570644567867525,"pose":{"rotation":{"radians":3.141592653589793},"translation":{"x":0.9345111039999995,"y":3.0}},"velocity":1.7320512509738308,"acceleration":-2.9999999999999343,"curvature":0,"holonomicRotation":102.40112616161753,"angularVelocity":0.0,"holonomicAngularVelocity":330.5293149167178},{"time":0.6604504707006249,"pose":{"rotation":{"radians":3.141592653589793},"translation":{"x":0.9286635519999995,"y":3.0}},"velocity":1.721893209232214,"acceleration":-2.9999999999999343,"curvature":0,"holonomicRotation":103.52030302086824,"angularVelocity":0.0,"holonomicAngularVelocity":329.5151752758652},{"time":0.6638404264006506,"pose":{"rotation":{"radians":3.141592653589793},"translation":{"x":0.9228436479999995,"y":3.0}},"velocity":1.711723342132137,"acceleration":-3.0,"curvature":0,"holonomicRotation":104.63734486753961,"angularVelocity":0.0,"holonomicAngularVelocity":328.5756668487767},{"time":0.667233040500551,"pose":{"rotation":{"radians":3.141592653589793},"translation":{"x":0.9170536959999995,"y":3.0}},"velocity":1.7015454998324355,"acceleration":-3.000000000000033,"curvature":0,"holonomicRotation":105.75207530777496,"angularVelocity":0.0,"holonomicAngularVelocity":327.7126337081664},{"time":0.6706269987753816,"pose":{"rotation":{"radians":3.141592653589793},"translation":{"x":0.9112959999999994,"y":3.0}},"velocity":1.6913636250079438,"acceleration":-3.0,"curvature":0,"holonomicRotation":106.86431831271531,"angularVelocity":0.0,"holonomicAngularVelocity":326.92816312821475},{"time":0.6740209551814752,"pose":{"rotation":{"radians":3.141592653589793},"translation":{"x":0.9055728639999996,"y":3.0}},"velocity":1.6811817557896627,"acceleration":-3.0000000000000653,"curvature":0,"holonomicRotation":107.97389824629674,"angularVelocity":0.0,"holonomicAngularVelocity":326.22459980402306},{"time":0.677413530871209,"pose":{"rotation":{"radians":3.141592653589793},"translation":{"x":0.8998865919999994,"y":3.0}},"velocity":1.6710040287204613,"acceleration":-2.999999999999967,"curvature":0,"holonomicRotation":109.08063989298502,"angularVelocity":0.0,"holonomicAngularVelocity":325.6045621060661},{"time":0.6808033132050937,"pose":{"rotation":{"radians":3.141592653589793},"translation":{"x":0.8942394879999994,"y":3.0}},"velocity":1.6608346817188075,"acceleration":-2.9999999999999343,"curvature":0,"holonomicRotation":110.18436848544441,"angularVelocity":0.0,"holonomicAngularVelocity":325.0709605936298},{"time":0.6841888547640234,"pose":{"rotation":{"radians":3.141592653589793},"translation":{"x":0.8886338559999994,"y":3.0}},"velocity":1.6506780570420185,"acceleration":-3.0,"curvature":0,"holonomicRotation":111.28490973213533,"angularVelocity":0.0,"holonomicAngularVelocity":324.6270190517883},{"time":0.6875686723648703,"pose":{"rotation":{"radians":3.141592653589793},"translation":{"x":0.8830719999999994,"y":3.0}},"velocity":1.6405386042394776,"acceleration":-3.000000000000033,"curvature":0,"holonomicRotation":112.38208984483704,"angularVelocity":0.0,"holonomicAngularVelocity":324.27629835830044},{"time":0.6909412460829945,"pose":{"rotation":{"radians":3.141592653589793},"translation":{"x":0.8775562239999994,"y":3.0}},"velocity":1.630420883085105,"acceleration":-3.000000000000033,"curvature":0,"holonomicRotation":113.47573556609083,"angularVelocity":0.0,"holonomicAngularVelocity":324.02272353900895},{"time":0.6943050182856477,"pose":{"rotation":{"radians":3.141592653589793},"translation":{"x":0.8720888319999994,"y":3.0}},"velocity":1.6203295664771453,"acceleration":-2.999999999999967,"curvature":0,"holonomicRotation":114.56567419655936,"angularVelocity":0.0,"holonomicAngularVelocity":323.8706144309882},{"time":0.6976583926806873,"pose":{"rotation":{"radians":3.141592653589793},"translation":{"x":0.8666721279999994,"y":3.0}},"velocity":1.6102694432920266,"acceleration":-3.0,"curvature":0,"holonomicRotation":115.65173362229797,"angularVelocity":0.0,"holonomicAngularVelocity":323.8247204431307},{"time":0.7009997333854816,"pose":{"rotation":{"radians":3.141592653589793},"translation":{"x":0.8613084159999995,"y":3.0}},"velocity":1.6002454211776436,"acceleration":-3.0000000000000333,"curvature":0,"holonomicRotation":116.73374234193324,"angularVelocity":0.0,"holonomicAngularVelocity":323.89025998968634},{"time":0.7043273640213842,"pose":{"rotation":{"radians":3.141592653589793},"translation":{"x":0.8559999999999994,"y":3.0}},"velocity":1.5902625292699357,"acceleration":-3.0000000000000333,"curvature":0,"holonomicRotation":117.81152949374537,"angularVelocity":0.0,"holonomicAngularVelocity":324.07296527170917},{"time":0.7076395668396712,"pose":{"rotation":{"radians":3.141592653589793},"translation":{"x":0.8507491839999994,"y":3.0}},"velocity":1.5803259208150744,"acceleration":-3.000000000000067,"curvature":0,"holonomicRotation":118.88492488264896,"angularVelocity":0.0,"holonomicAngularVelocity":324.3791332025104},{"time":0.7109345818853914,"pose":{"rotation":{"radians":3.141592653589793},"translation":{"x":0.8455582719999994,"y":3.0}},"velocity":1.5704408756779138,"acceleration":-3.0000000000000338,"curvature":0,"holonomicRotation":119.9537590070689,"angularVelocity":0.0,"holonomicAngularVelocity":324.815683417525},{"time":0.7142106062061442,"pose":{"rotation":{"radians":3.141592653589793},"translation":{"x":0.8404295679999996,"y":3.0}},"velocity":1.5606128027156554,"acceleration":-3.0,"curvature":0,"holonomicRotation":121.01786308570665,"angularVelocity":0.0,"holonomicAngularVelocity":325.3902244825922},{"time":0.7174657931134039,"pose":{"rotation":{"radians":3.141592653589793},"translation":{"x":0.8353653759999995,"y":3.0}},"velocity":1.5508472419938761,"acceleration":-3.0000000000000684,"curvature":0,"holonomicRotation":122.07706908419267,"angularVelocity":0.0,"holonomicAngularVelocity":326.1111296260469},{"time":0.7206982515046193,"pose":{"rotation":{"radians":3.141592653589793},"translation":{"x":0.8303679999999996,"y":3.0}},"velocity":1.54114986682023,"acceleration":-2.999999999999966,"curvature":0,"holonomicRotation":123.13120974162113,"angularVelocity":0.0,"holonomicAngularVelocity":326.9876235749752},{"time":0.7239060452549554,"pose":{"rotation":{"radians":3.141592653589793},"translation":{"x":0.8254397439999994,"y":3.0}},"velocity":1.5315264855692217,"acceleration":-3.0,"curvature":0,"holonomicRotation":124.18011859696219,"angularVelocity":0.0,"holonomicAngularVelocity":328.0298823898185},{"time":0.7270871926881824,"pose":{"rotation":{"radians":3.141592653589793},"translation":{"x":0.8205829119999994,"y":3.0}},"velocity":1.5219830432695403,"acceleration":-3.0000000000000697,"curvature":0,"holonomicRotation":125.22363001534833,"angularVelocity":0.0,"holonomicAngularVelocity":329.2491485731567},{"time":0.7302396661368747,"pose":{"rotation":{"radians":3.141592653589793},"translation":{"x":0.8157998079999994,"y":3.0}},"velocity":1.5125256229234634,"acceleration":-3.0,"curvature":0,"holonomicRotation":126.26157921422976,"angularVelocity":0.0,"holonomicAngularVelocity":330.65786420328374},{"time":0.7333613916027216,"pose":{"rotation":{"radians":3.141592653589793},"translation":{"x":0.8110927359999994,"y":3.0}},"velocity":1.5031604465259225,"acceleration":-3.000000000000071,"curvature":0,"holonomicRotation":127.29380228939569,"angularVelocity":0.0,"holonomicAngularVelocity":332.2698254257273},{"time":0.7364502485284024,"pose":{"rotation":{"radians":3.141592653589793},"translation":{"x":0.8064639999999995,"y":3.0}},"velocity":1.4938938757488804,"acceleration":-2.999999999999964,"curvature":0,"holonomicRotation":128.32013624085667,"angularVelocity":0.0,"holonomicAngularVelocity":334.10036236743434},{"time":0.7395040696930898,"pose":{"rotation":{"radians":3.141592653589793},"translation":{"x":0.8019159039999995,"y":3.0}},"velocity":1.484732412254818,"acceleration":-3.0000000000000364,"curvature":0,"holonomicRotation":129.34041899858408,"angularVelocity":0.0,"holonomicAngularVelocity":336.16654944943934},{"time":0.7425206412442442,"pose":{"rotation":{"radians":3.141592653589793},"translation":{"x":0.7974507519999996,"y":3.0}},"velocity":1.4756826976013548,"acceleration":-2.999999999999963,"curvature":0,"holonomicRotation":130.354489448103,"angularVelocity":0.0,"holonomicAngularVelocity":338.48745222403613},{"time":0.7454977028789072,"pose":{"rotation":{"radians":3.141592653589793},"translation":{"x":0.7930708479999995,"y":3.0}},"velocity":1.4667515126973658,"acceleration":-3.0000000000000746,"curvature":0,"holonomicRotation":131.362187455934,"angularVelocity":0.0,"holonomicAngularVelocity":341.0844183201534},{"time":0.7484329481881968,"pose":{"rotation":{"radians":3.141592653589793},"translation":{"x":0.7887784959999995,"y":3.0}},"velocity":1.4579457767694965,"acceleration":-3.0000000000000755,"curvature":0,"holonomicRotation":132.36335389488002,"angularVelocity":0.0,"holonomicAngularVelocity":343.9814219379624},{"time":0.7513240251791333,"pose":{"rotation":{"radians":3.141592653589793},"translation":{"x":0.7845759999999995,"y":3.0}},"velocity":1.449272545796687,"acceleration":-3.0,"curvature":0,"holonomicRotation":133.35783066915448,"angularVelocity":0.0,"holonomicAngularVelocity":347.20547372180556},{"time":0.7541685369882507,"pose":{"rotation":{"radians":3.141592653589793},"translation":{"x":0.7804656639999995,"y":3.0}},"velocity":1.440739010369335,"acceleration":-3.0,"curvature":0,"holonomicRotation":134.34546073934635,"angularVelocity":0.0,"holonomicAngularVelocity":350.787110926239},{"time":0.7569640428016853,"pose":{"rotation":{"radians":3.141592653589793},"translation":{"x":0.7764497919999995,"y":3.0}},"velocity":1.4323524929290314,"acceleration":-2.9999999999999205,"curvature":0,"holonomicRotation":135.32608814721857,"angularVelocity":0.0,"holonomicAngularVelocity":354.7609868148111},{"time":0.7597080589965249,"pose":{"rotation":{"radians":3.141592653589793},"translation":{"x":0.7725306879999996,"y":3.0}},"velocity":1.4241204443445123,"acceleration":-3.0000000000000404,"curvature":0,"holonomicRotation":136.2995580403357,"angularVelocity":0.0,"holonomicAngularVelocity":359.1665835168236},{"time":0.7623980605181608,"pose":{"rotation":{"radians":3.141592653589793},"translation":{"x":0.7687106559999997,"y":3.0}},"velocity":1.4160504397796045,"acceleration":-3.0000000000000413,"curvature":0,"holonomicRotation":137.26571669651673,"angularVelocity":0.0,"holonomicAngularVelocity":364.0490795752349},{"time":0.7650314825081619,"pose":{"rotation":{"radians":3.141592653589793},"translation":{"x":0.7649919999999996,"y":3.0}},"velocity":1.4081501738096016,"acceleration":-2.9999999999999156,"curvature":0,"holonomicRotation":138.2244115481098,"angularVelocity":0.0,"holonomicAngularVelocity":369.46041278826016},{"time":0.7676057221967847,"pose":{"rotation":{"radians":3.141592653589793},"translation":{"x":0.7613770239999995,"y":3.0}},"velocity":1.4004274547437332,"acceleration":-3.0,"curvature":0,"holonomicRotation":139.1754912060843,"angularVelocity":0.0,"holonomicAngularVelocity":375.46059160551147},{"time":0.7701181410736074,"pose":{"rotation":{"radians":3.141592653589793},"translation":{"x":0.7578680319999995,"y":3.0}},"velocity":1.392890198113265,"acceleration":-2.9999999999999556,"curvature":0,"holonomicRotation":140.11880548393702,"angularVelocity":0.0,"holonomicAngularVelocity":382.1193256137865},{"time":0.7725660673489108,"pose":{"rotation":{"radians":3.141592653589793},"translation":{"x":0.7544673279999996,"y":3.0}},"velocity":1.3855464192873552,"acceleration":-2.9999999999999547,"curvature":0,"holonomicRotation":141.0542054214082,"angularVelocity":0.0,"holonomicAngularVelocity":389.518069490963},{"time":0.7749467987173114,"pose":{"rotation":{"radians":3.141592653589793},"translation":{"x":0.7511772159999996,"y":3.0}},"velocity":1.378404225182153,"acceleration":-3.0000000000000466,"curvature":0,"holonomicRotation":141.9815433080042,"angularVelocity":0.0,"holonomicAngularVelocity":397.75260811696825},{"time":0.7772576054337521,"pose":{"rotation":{"radians":3.141592653589793},"translation":{"x":0.7479999999999997,"y":3.0}},"velocity":1.3714718050328312,"acceleration":-2.999999999999952,"curvature":0,"holonomicRotation":142.9006727063227,"angularVelocity":0.0,"holonomicAngularVelocity":406.9363576767022},{"time":0.7794957337102569,"pose":{"rotation":{"radians":3.141592653589793},"translation":{"x":0.7449379839999997,"y":3.0}},"velocity":1.3647574202033166,"acceleration":-3.0000000000000497,"curvature":0,"holonomicRotation":143.8114484751768,"angularVelocity":0.0,"holonomicAngularVelocity":417.2046252648769},{"time":0.7816584094398583,"pose":{"rotation":{"radians":3.141592653589793},"translation":{"x":0.7419934719999997,"y":3.0}},"velocity":1.3582693930145124,"acceleration":-3.0,"curvature":0,"holonomicRotation":144.7137267925146,"angularVelocity":0.0,"holonomicAngularVelocity":428.72016814687754},{"time":0.7837428422517746,"pose":{"rotation":{"radians":3.141592653589793},"translation":{"x":0.7391687679999996,"y":3.0}},"velocity":1.3520160945787636,"acceleration":-3.0,"curvature":0,"holonomicRotation":145.6073651781302,"angularVelocity":0.0,"holonomicAngularVelocity":441.68054002804604},{"time":0.7857462298992738,"pose":{"rotation":{"radians":3.141592653589793},"translation":{"x":0.7364661759999996,"y":3.0}},"velocity":1.3460059316362658,"acceleration":-3.000000000000111,"curvature":0,"holonomicRotation":146.49222251616317,"angularVelocity":0.0,"holonomicAngularVelocity":456.32793235636615},{"time":0.7876657629786886,"pose":{"rotation":{"radians":3.141592653589793},"translation":{"x":0.7338879999999997,"y":3.0}},"velocity":1.3402473323980213,"acceleration":-3.0,"curvature":0,"holonomicRotation":147.3681590773822,"angularVelocity":0.0,"holonomicAngularVelocity":472.96255850612283},{"time":0.7894986299747696,"pose":{"rotation":{"radians":3.141592653589793},"translation":{"x":0.7314365439999997,"y":3.0}},"velocity":1.3347487314097783,"acceleration":-3.0,"curvature":0,"holonomicRotation":148.23503654125008,"angularVelocity":0.0,"holonomicAngularVelocity":491.96116371169336},{"time":0.7912420226239885,"pose":{"rotation":{"radians":3.141592653589793},"translation":{"x":0.7291141119999998,"y":3.0}},"velocity":1.3295185534621219,"acceleration":-2.9999999999999365,"curvature":0,"holonomicRotation":149.0927180177662,"angularVelocity":0.0,"holonomicAngularVelocity":513.8031069154317},{"time":0.7928931415835634,"pose":{"rotation":{"radians":3.141592653589793},"translation":{"x":0.7269230079999998,"y":3.0}},"velocity":1.3245651965833969,"acceleration":-3.0000000000001346,"curvature":0,"holonomicRotation":149.94106806908277,"angularVelocity":0.0,"holonomicAngularVelocity":539.1078924357475},{"time":0.7944492023899066,"pose":{"rotation":{"radians":3.141592653589793},"translation":{"x":0.7248655359999997,"y":3.0}},"velocity":1.3198970141643676,"acceleration":-2.9999999999998574,"curvature":0,"holonomicRotation":150.77995273089232,"angularVelocity":0.0,"holonomicAngularVelocity":568.6904782690121},{"time":0.7959074416859362,"pose":{"rotation":{"radians":3.141592653589793},"translation":{"x":0.7229439999999998,"y":3.0}},"velocity":1.3155222962762787,"acceleration":-3.0,"curvature":0,"holonomicRotation":151.60923953358207,"angularVelocity":0.0,"holonomicAngularVelocity":603.6450256535591},{"time":0.797265123692316,"pose":{"rotation":{"radians":3.141592653589793},"translation":{"x":0.7211607039999998,"y":3.0}},"velocity":1.3114492502571393,"acceleration":-3.0000000000000817,"curvature":0,"holonomicRotation":152.42879752315255,"angularVelocity":0.0,"holonomicAngularVelocity":645.4757518441586},{"time":0.798519546893235,"pose":{"rotation":{"radians":3.141592653589793},"translation":{"x":0.7195179519999998,"y":3.0}},"velocity":1.3076859806543821,"acceleration":-3.0,"curvature":0,"holonomicRotation":153.23849728189654,"angularVelocity":0.0,"holonomicAngularVelocity":696.3089899516729},{"time":0.79966805090292,"pose":{"rotation":{"radians":3.141592653589793},"translation":{"x":0.7180180479999998,"y":3.0}},"velocity":1.3042404686253273,"acceleration":-2.999999999999807,"curvature":0,"holonomicRotation":154.03821094883577,"angularVelocity":0.0,"holonomicAngularVelocity":759.252034595326},{"time":0.8007080234747378,"pose":{"rotation":{"radians":3.141592653589793},"translation":{"x":0.7166632959999999,"y":3.0}},"velocity":1.301120550909874,"acceleration":-3.0,"curvature":0,"holonomicRotation":154.82781223991174,"angularVelocity":0.0,"holonomicAngularVelocity":839.0327683629985},{"time":0.8016369076106172,"pose":{"rotation":{"radians":3.141592653589793},"translation":{"x":0.7154559999999999,"y":3.0}},"velocity":1.2983338985022357,"acceleration":-3.0,"curvature":0,"holonomicRotation":155.60717646792713,"angularVelocity":0.0,"holonomicAngularVelocity":943.2148209476935},{"time":0.8024522087246688,"pose":{"rotation":{"radians":3.141592653589793},"translation":{"x":0.714398464,"y":3.0}},"velocity":1.295887995160081,"acceleration":-2.9999999999998637,"curvature":0,"holonomicRotation":156.37618056223576,"angularVelocity":0.0,"holonomicAngularVelocity":1084.6990200548287},{"time":0.8031515018114298,"pose":{"rotation":{"radians":3.141592653589793},"translation":{"x":0.7134929919999998,"y":3.0}},"velocity":1.2937901158997982,"acceleration":-2.999999999999841,"curvature":0,"holonomicRotation":157.1347030881765,"angularVelocity":0.0,"holonomicAngularVelocity":1287.4399354950756},{"time":0.8037324385661883,"pose":{"rotation":{"radians":3.141592653589793},"translation":{"x":0.7127418879999999,"y":3.0}},"velocity":1.2920473056355228,"acceleration":-3.0,"curvature":0,"holonomicRotation":157.88262426624945,"angularVelocity":0.0,"holonomicAngularVelocity":1601.5128454902845},{"time":0.8041927544024657,"pose":{"rotation":{"radians":3.141592653589793},"translation":{"x":0.712147456,"y":3.0}},"velocity":1.2906663581266904,"acceleration":-3.0,"curvature":0,"holonomicRotation":158.61982599103044,"angularVelocity":0.0,"holonomicAngularVelocity":2152.0618205680316},{"time":0.8045302753100199,"pose":{"rotation":{"radians":3.141592653589793},"translation":{"x":0.711712,"y":3.0}},"velocity":1.2896537954040281,"acceleration":-2.999999999999671,"curvature":0,"holonomicRotation":159.34619184982114,"angularVelocity":0.0,"holonomicAngularVelocity":3364.2982860706516},{"time":0.8047429244957871,"pose":{"rotation":{"radians":3.141592653589793},"translation":{"x":0.711437824,"y":3.0}},"velocity":1.2890158478467264,"acceleration":-3.0,"curvature":0,"holonomicRotation":160.0616071410322,"angularVelocity":0.0,"holonomicAngularVelocity":8208.820848444744},{"time":0.8048287287500482,"pose":{"rotation":{"radians":3.141592653589793},"translation":{"x":0.7113272319999999,"y":3.0}},"velocity":1.2887584350839432,"acceleration":-3.0,"curvature":0,"holonomicRotation":160.7659588922958,"angularVelocity":73215.99808492587,"holonomicAngularVelocity":16154.750305452018},{"time":0.8048716373046778,"pose":{"rotation":{"radians":0.0},"translation":{"x":0.711382528,"y":3.0}},"velocity":1.2886297094200543,"acceleration":-3.0,"curvature":0,"holonomicRotation":161.4591358783053,"angularVelocity":0.0,"holonomicAngularVelocity":3930.9933495205482},{"time":0.8050451030675128,"pose":{"rotation":{"radians":0.0},"translation":{"x":0.7116060160000001,"y":3.0}},"velocity":1.2881093121315492,"acceleration":-3.00000000000128,"curvature":0,"holonomicRotation":162.14102863837897,"angularVelocity":0.0,"holonomicAngularVelocity":2191.3850933124963},{"time":0.8053510743262443,"pose":{"rotation":{"radians":0.0},"translation":{"x":0.7120000000000001,"y":3.0}},"velocity":1.2871913983553545,"acceleration":-3.000000000000363,"curvature":0,"holonomicRotation":162.81152949374535,"angularVelocity":0.0,"holonomicAngularVelocity":1495.8566160096339},{"time":0.8057916266250063,"pose":{"rotation":{"radians":0.0},"translation":{"x":0.7125667840000002,"y":3.0}},"velocity":1.2858697414590687,"acceleration":-2.999999999999748,"curvature":0,"holonomicRotation":163.47053256454666,"angularVelocity":0.0,"holonomicAngularVelocity":1121.3457867665288},{"time":0.8063689696976357,"pose":{"rotation":{"radians":0.0},"translation":{"x":0.7133086720000001,"y":3.0}},"velocity":1.2841377122411803,"acceleration":-3.0,"curvature":0,"holonomicRotation":164.11793378655855,"angularVelocity":0.0,"holonomicAngularVelocity":887.2435763310082},{"time":0.8070854551792139,"pose":{"rotation":{"radians":0.0},"translation":{"x":0.7142279680000001,"y":3.0}},"velocity":1.2819882557964455,"acceleration":-3.00000000000031,"curvature":0,"holonomicRotation":164.75363092762325,"angularVelocity":0.0,"holonomicAngularVelocity":727.0374848904387},{"time":0.8079435851781969,"pose":{"rotation":{"radians":0.0},"translation":{"x":0.7153269760000002,"y":3.0}},"velocity":1.2794138657994965,"acceleration":-3.000000000000259,"curvature":0,"holonomicRotation":165.37752360379284,"angularVelocity":0.0,"holonomicAngularVelocity":610.5021260858708},{"time":0.8089460218041138,"pose":{"rotation":{"radians":0.0},"translation":{"x":0.7166080000000001,"y":3.0}},"velocity":1.2764065559217455,"acceleration":-3.0000000000002216,"curvature":0,"holonomicRotation":165.98951329518147,"angularVelocity":0.0,"holonomicAngularVelocity":521.9229429634715},{"time":0.8100955977605455,"pose":{"rotation":{"radians":0.0},"translation":{"x":0.7180733440000002,"y":3.0}},"velocity":1.2729578280524503,"acceleration":-3.0,"curvature":0,"holonomicRotation":166.58950336152236,"angularVelocity":0.0,"holonomicAngularVelocity":452.3212733824633},{"time":0.8113953281303116,"pose":{"rotation":{"radians":0.0},"translation":{"x":0.7197253120000002,"y":3.0}},"velocity":1.2690586369431522,"acceleration":-2.9999999999999147,"curvature":0,"holonomicRotation":167.1773990574288,"angularVelocity":0.0,"holonomicAngularVelocity":396.19456639109796},{"time":0.8128484235000198,"pose":{"rotation":{"radians":0.0},"translation":{"x":0.7215662080000004,"y":3.0}},"velocity":1.2646993508340274,"acceleration":-3.0,"curvature":0,"holonomicRotation":167.75310754735528,"angularVelocity":0.0,"holonomicAngularVelocity":349.9826009931239},{"time":0.814458304594975,"pose":{"rotation":{"radians":0.0},"translation":{"x":0.7235983360000003,"y":3.0}},"velocity":1.2598697075491618,"acceleration":-3.0,"curvature":0,"holonomicRotation":168.31653792025736,"angularVelocity":0.0,"holonomicAngularVelocity":311.27996205689834},{"time":0.8162286186237004,"pose":{"rotation":{"radians":0.0},"translation":{"x":0.7258240000000004,"y":3.0}},"velocity":1.2545587654629855,"acceleration":-3.0000000000000626,"curvature":0,"holonomicRotation":168.8676012039478,"angularVelocity":0.0,"holonomicAngularVelocity":278.4029431612908},{"time":0.8181632575649491,"pose":{"rotation":{"radians":0.0},"translation":{"x":0.7282455040000004,"y":3.0}},"velocity":1.2487548486392395,"acceleration":-3.0,"curvature":0,"holonomicRotation":169.40621037914588,"angularVelocity":0.0,"holonomicAngularVelocity":250.13776559804487},{"time":0.8202663786702946,"pose":{"rotation":{"radians":0.0},"translation":{"x":0.7308651520000005,"y":3.0}},"velocity":1.242445485323203,"acceleration":-3.0,"curvature":0,"holonomicRotation":169.9322803932191,"angularVelocity":0.0,"holonomicAngularVelocity":225.58733049096767},{"time":0.8225424275036987,"pose":{"rotation":{"radians":0.0},"translation":{"x":0.7336852480000005,"y":3.0}},"velocity":1.2356173388229907,"acceleration":-3.000000000000049,"curvature":0,"holonomicRotation":170.4457281736138,"angularVelocity":0.0,"holonomicAngularVelocity":204.07427161529972},{"time":0.8249961638977877,"pose":{"rotation":{"radians":0.0},"translation":{"x":0.7367080960000004,"y":3.0}},"velocity":1.2282561296407235,"acceleration":-3.0,"curvature":0,"holonomicRotation":170.94647264097347,"angularVelocity":0.0,"holonomicAngularVelocity":185.07757012030268},{"time":0.827632691277368,"pose":{"rotation":{"radians":0.0},"translation":{"x":0.7399360000000006,"y":3.0}},"velocity":1.2203465475019826,"acceleration":-3.0,"curvature":0,"holonomicRotation":171.43443472194184,"angularVelocity":0.0,"holonomicAngularVelocity":168.1899155821377},{"time":0.8304574898871029,"pose":{"rotation":{"radians":0.0},"translation":{"x":0.7433712640000005,"y":3.0}},"velocity":1.2118721516727782,"acceleration":-2.9999999999999605,"curvature":0,"holonomicRotation":171.90953736164968,"angularVelocity":0.0,"holonomicAngularVelocity":153.08830123711394},{"time":0.8334764545662989,"pose":{"rotation":{"radians":0.0},"translation":{"x":0.7470161920000006,"y":3.0}},"velocity":1.20281525763519,"acceleration":-3.0,"curvature":0,"holonomicRotation":172.37170553588265,"angularVelocity":0.0,"holonomicAngularVelocity":139.51329707778163},{"time":0.8366959378446228,"pose":{"rotation":{"radians":0.0},"translation":{"x":0.7508730880000007,"y":3.0}},"velocity":1.1931568078002186,"acceleration":-2.999999999999931,"curvature":0,"holonomicRotation":172.8208662629284,"angularVelocity":0.0,"holonomicAngularVelocity":127.25415324391982},{"time":0.8401227992951643,"pose":{"rotation":{"radians":0.0},"translation":{"x":0.7549442560000007,"y":3.0}},"velocity":1.182876223448594,"acceleration":-3.0,"curvature":0,"holonomicRotation":173.2569486151013,"angularVelocity":0.0,"holonomicAngularVelocity":116.13790624520176},{"time":0.8437644622845802,"pose":{"rotation":{"radians":0.0},"translation":{"x":0.7592320000000008,"y":3.0}},"velocity":1.1719512344803464,"acceleration":-2.9999999999999694,"curvature":0,"holonomicRotation":173.6798837299427,"angularVelocity":0.0,"holonomicAngularVelocity":106.0212871638359},{"time":0.8476289795160991,"pose":{"rotation":{"radians":0.0},"translation":{"x":0.7637386240000008,"y":3.0}},"velocity":1.16035768278579,"acceleration":-3.0,"curvature":0,"holonomicRotation":174.08960482109515,"angularVelocity":0.0,"holonomicAngularVelocity":96.78462582377615},{"time":0.8517251090860519,"pose":{"rotation":{"radians":0.0},"translation":{"x":0.7684664320000009,"y":3.0}},"velocity":1.1480692940759316,"acceleration":-2.999999999999946,"curvature":0,"holonomicRotation":174.48604718884874,"angularVelocity":0.0,"holonomicAngularVelocity":88.32719947509531},{"time":0.8560624031900854,"pose":{"rotation":{"radians":0.0},"translation":{"x":0.773417728000001,"y":3.0}},"velocity":1.135057411763831,"acceleration":-3.0000000000000258,"curvature":0,"holonomicRotation":174.86914823035787,"angularVelocity":0.0,"holonomicAngularVelocity":80.56364209989418},{"time":0.8606513121511621,"pose":{"rotation":{"radians":0.0},"translation":{"x":0.7785948160000009,"y":3.0}},"velocity":1.121290684880601,"acceleration":-3.0,"curvature":0,"holonomicRotation":175.23884744952704,"angularVelocity":0.0,"holonomicAngularVelocity":73.42114283374042},{"time":0.8655033071390841,"pose":{"rotation":{"radians":0.0},"translation":{"x":0.7840000000000009,"y":3.0}},"velocity":1.1067346999168353,"acceleration":-2.9999999999999543,"curvature":0,"holonomicRotation":175.59508646656386,"angularVelocity":0.0,"holonomicAngularVelocity":66.83723868873658},{"time":0.8706310258683112,"pose":{"rotation":{"radians":0.0},"translation":{"x":0.7896355840000009,"y":3.0}},"velocity":1.091351543729154,"acceleration":-2.9999999999999565,"curvature":0,"holonomicRotation":175.93780902719791,"angularVelocity":0.0,"holonomicAngularVelocity":60.75805993075559},{"time":0.8760484467790695,"pose":{"rotation":{"radians":0.0},"translation":{"x":0.795503872000001,"y":3.0}},"velocity":1.0750992809968791,"acceleration":-3.000000000000041,"curvature":0,"holonomicRotation":176.2669610115639,"angularVelocity":0.0,"holonomicAngularVelocity":55.136923864247166},{"time":0.881771098843605,"pose":{"rotation":{"radians":0.0},"translation":{"x":0.801607168000001,"y":3.0}},"velocity":1.0579313248032722,"acceleration":-3.0000000000000195,"curvature":0,"holonomicRotation":176.58249044274777,"angularVelocity":0.0,"holonomicAngularVelocity":49.933199445933845},{"time":0.8878163163661428,"pose":{"rotation":{"radians":0.0},"translation":{"x":0.8079477760000011,"y":3.0}},"velocity":1.039795672235659,"acceleration":-3.000000000000018,"curvature":0,"holonomicRotation":176.8843474949947,"angularVelocity":0.0,"holonomicAngularVelocity":45.11138440886719},{"time":0.8942035512151246,"pose":{"rotation":{"radians":0.0},"translation":{"x":0.8145280000000011,"y":3.0}},"velocity":1.0206339676887135,"acceleration":-2.9999999999999827,"curvature":0,"holonomicRotation":177.17248450157683,"angularVelocity":0.0,"holonomicAngularVelocity":40.64035065747553},{"time":0.9009547592215794,"pose":{"rotation":{"radians":0.0},"translation":{"x":0.8213501440000013,"y":3.0}},"velocity":1.0003803436693492,"acceleration":-2.9999999999999836,"curvature":0,"holonomicRotation":177.4468559623207,"angularVelocity":0.0,"holonomicAngularVelocity":36.49272410852757},{"time":0.9080948835843534,"pose":{"rotation":{"radians":0.0},"translation":{"x":0.8284165120000012,"y":3.0}},"velocity":0.9789599705810272,"acceleration":-3.0,"curvature":0,"holonomicRotation":177.707418550792,"angularVelocity":0.0,"holonomicAngularVelocity":32.64437295112772},{"time":0.9156524669606622,"pose":{"rotation":{"radians":0.0},"translation":{"x":0.8357294080000013,"y":3.0}},"velocity":0.9562872204521011,"acceleration":-2.9999999999999853,"curvature":0,"holonomicRotation":177.95413112113746,"angularVelocity":0.0,"holonomicAngularVelocity":29.07398421401291},{"time":0.9236604369633628,"pose":{"rotation":{"radians":0.0},"translation":{"x":0.8432911360000014,"y":3.0}},"velocity":0.9322633104439995,"acceleration":-2.9999999999999862,"curvature":0,"holonomicRotation":178.18695471458227,"angularVelocity":0.0,"holonomicAngularVelocity":25.76271308828699},{"time":0.9321571294603682,"pose":{"rotation":{"radians":0.0},"translation":{"x":0.8511040000000014,"y":3.0}},"velocity":0.906773232952983,"acceleration":-3.000000000000013,"curvature":0,"holonomicRotation":178.40585256558202,"angularVelocity":0.0,"holonomicAngularVelocity":22.693893042798674},{"time":0.9411876444830668,"pose":{"rotation":{"radians":0.0},"translation":{"x":0.8591703040000015,"y":3.0}},"velocity":0.8796816878848872,"acceleration":-3.0,"curvature":0,"holonomicRotation":178.61079010762853,"angularVelocity":0.0,"holonomicAngularVelocity":19.852797684511415},{"time":0.9508056778763441,"pose":{"rotation":{"radians":0.0},"translation":{"x":0.8674923520000015,"y":3.0}},"velocity":0.8508275877050555,"acceleration":-2.9999999999999885,"curvature":0,"holonomicRotation":178.80173497870814,"angularVelocity":0.0,"holonomicAngularVelocity":17.226447801526522},{"time":0.9610760510689227,"pose":{"rotation":{"radians":0.0},"translation":{"x":0.8760724480000016,"y":3.0}},"velocity":0.8200164681273197,"acceleration":-3.0,"curvature":0,"holonomicRotation":178.9786570264123,"angularVelocity":0.0,"holonomicAngularVelocity":14.803459309434144},{"time":0.9720782960767862,"pose":{"rotation":{"radians":0.0},"translation":{"x":0.8849128960000017,"y":3.0}},"velocity":0.7870097331037292,"acceleration":-2.99999999999999,"curvature":0,"holonomicRotation":179.14152831269863,"angularVelocity":0.0,"holonomicAngularVelocity":12.573930155256075},{"time":0.9839118917598498,"pose":{"rotation":{"radians":0.0},"translation":{"x":0.8940160000000017,"y":3.0}},"velocity":0.7515089460545383,"acceleration":-3.0,"curvature":0,"holonomicRotation":179.290323118303,"angularVelocity":0.0,"holonomicAngularVelocity":10.52936695080417},{"time":0.9967041924866741,"pose":{"rotation":{"radians":0.0},"translation":{"x":0.9033840640000018,"y":3.0}},"velocity":0.7131320438740657,"acceleration":-2.999999999999991,"curvature":0,"holonomicRotation":179.42501794680078,"angularVelocity":0.0,"holonomicAngularVelocity":8.662655725035885},{"time":1.0106229704392349,"pose":{"rotation":{"radians":0.0},"translation":{"x":0.9130193920000018,"y":3.0}},"velocity":0.6713757100163831,"acceleration":-3.000000000000016,"curvature":0,"holonomicRotation":179.54559152831703,"angularVelocity":0.0,"holonomicAngularVelocity":6.968086561525102},{"time":1.0258973637219186,"pose":{"rotation":{"radians":0.0},"translation":{"x":0.9229242880000019,"y":3.0}},"velocity":0.6255525301683319,"acceleration":-2.999999999999993,"curvature":0,"holonomicRotation":179.65202482288555,"angularVelocity":0.0,"holonomicAngularVelocity":5.441450458318903},{"time":1.0428553791033977,"pose":{"rotation":{"radians":0.0},"translation":{"x":0.9331010560000019,"y":3.0}},"velocity":0.5746784840238947,"acceleration":-3.000000000000013,"curvature":0,"holonomicRotation":179.74430102345528,"angularVelocity":0.0,"holonomicAngularVelocity":4.080240391385063},{"time":1.0619975196630789,"pose":{"rotation":{"radians":0.0},"translation":{"x":0.943552000000002,"y":3.0}},"velocity":0.517252062344851,"acceleration":-3.0,"curvature":0,"holonomicRotation":179.82240555854446,"angularVelocity":0.0,"holonomicAngularVelocity":2.8840050791060468},{"time":1.0841613280627944,"pose":{"rotation":{"radians":0.0},"translation":{"x":0.954279424000002,"y":3.0}},"velocity":0.45076063714570447,"acceleration":-2.999999999999995,"curvature":0,"holonomicRotation":179.88632609454157,"angularVelocity":0.0,"holonomicAngularVelocity":1.85486946202017},{"time":1.11096992248394,"pose":{"rotation":{"radians":0.0},"translation":{"x":0.9652856320000022,"y":3.0}},"velocity":0.3703348538822674,"acceleration":-3.0000000000000124,"curvature":0,"holonomicRotation":179.93605253765304,"angularVelocity":0.0,"holonomicAngularVelocity":0.9974097157085644},{"time":1.146586677849842,"pose":{"rotation":{"radians":0.0},"translation":{"x":0.9765729280000022,"y":3.0}},"velocity":0.2634845877845615,"acceleration":-3.000000000000003,"curvature":0,"holonomicRotation":179.971577035497,"angularVelocity":0.0,"holonomicAngularVelocity":0.24271183782351305},{"time":1.2344148737780292,"pose":{"rotation":{"radians":0.0},"translation":{"x":0.9881436160000022,"y":3.0}},"velocity":0,"acceleration":-2.9999999999999973,"curvature":0,"holonomicRotation":179.99289397834346,"angularVelocity":0.0,"holonomicAngularVelocity":0.0}]